{
"instructions_readme": "1) Open Chrome, 2) go to chrome://tracing, 3) click Load, 4) navigate to this file.",

"traceEvents":[
{ "pid": "Unity", "ph":"M", "name": "process_name", "args": {"name": "Unity"} },
{ "pid": "Unity", "ph":"M", "name": "process_sort_index", "args": {"sort_index": -100} },
{ "pid": "Unity", "tid": 1, "ph":"M", "name": "thread_name", "args": {"name": ""} },
{ "pid": "Unity", "tid": 1,"ts": 10073837548.7,"dur": 5946836.9, "ph":"X", "name": "Build player"},
{ "pid": "Unity", "tid": 1,"ts": 10073855110.8,"dur": 29679.7, "ph":"X", "name": "Preprocess Player"},
{ "pid": "Unity", "tid": 1,"ts": 10073910280.2,"dur": 5827871.3, "ph":"X", "name": "Prepare For Build"},
{}

],
"meta_datetime": "07/15/2021 01:51:23",
"meta_command_line": "\"C:\\Program Files\\Unity\\Hub\\Editor\\2021.2.0b3\\Editor\\Unity.exe\" -projectpath \"O:/1. Programming/Project/MedievalGame/Medieval Game\" -useHub -hubIPC -cloudEnvironment production -skipUpgradeDialogs -hubSessionId bced8f10-e4de-11eb-a53d-2353ee33132f -accessToken 3HTgvAooCJbb19TwlQN6xOmm8arGhw3TcqmKVOCwkGw009f",
"meta_command_line_args": "C:\\Program Files\\Unity\\Hub\\Editor\\2021.2.0b3\\Editor\\Unity.exe -projectpath O:/1. Programming/Project/MedievalGame/Medieval Game -useHub -hubIPC -cloudEnvironment production -skipUpgradeDialogs -hubSessionId bced8f10-e4de-11eb-a53d-2353ee33132f -accessToken 3HTgvAooCJbb19TwlQN6xOmm8arGhw3TcqmKVOCwkGw009f",
"meta_user_name": "kalas",
"meta_os_version": "Microsoft Windows NT 10.0.19042.0",
"meta_cpu_count": "12"
}
